treedir/__init__.py
treedir/base.py
treedir/builder.py
treedir-29082022.dist-info/WHEEL
treedir-29082022.dist-info/METADATA
treedir-29082022.dist-info/RECORD
