Metadata-Version: 2.1
Name: treedir
Version: 29082022
Summary: Module to create tree graphs for files and directories based in a simple structured language
License: GPLv3
Author: David Pineda
Author-email: dahalpi@gmail.com
Requires-Python: >=3.9,<4.0
Classifier: License :: Other/Proprietary License
Classifier: Programming Language :: Python :: 3
Classifier: Programming Language :: Python :: 3.10
Classifier: Programming Language :: Python :: 3.9
Requires-Dist: anytree (>=2.8.0,<3.0.0)
Requires-Dist: click (>=8.1.3,<9.0.0)
